indic_num2words-1.3.2.dist-info/licenses/LICENSE
num_to_words/__init__.py
num_to_words/exception.py
num_to_words/version.py
num_to_words/utils/__init__.py
num_to_words/utils/constants.py
indic_num2words-1.3.2.dist-info/METADATA
indic_num2words-1.3.2.dist-info/WHEEL
indic_num2words-1.3.2.dist-info/top_level.txt
indic_num2words-1.3.2.dist-info/RECORD
