Metadata-Version: 2.4
Name: indic-num2words
Version: 1.3.2
Summary: Package to convert numbers to words with support of multiple indian languages.
Home-page: https://github.com/sutariyaraj/indic-num2words/
Author: Indic-Num2Words Contributors
Author-email: sutariyaraj77725@gmail.com
License: Apache License
Project-URL: Source, https://github.com/sutariyaraj/indic-num2words/
Project-URL: Tracker, https://github.com/sutariyaraj/indic-num2words/issues
Keywords: python,indic,languages,text to speech,TTS,setup.py
Classifier: Development Status :: 5 - Production/Stable
Classifier: Intended Audience :: Developers
Classifier: Intended Audience :: Customer Service
Classifier: Natural Language :: English
Classifier: License :: OSI Approved :: Apache Software License
Classifier: Programming Language :: Python :: 3.9
Classifier: Topic :: Communications
Classifier: Topic :: Software Development :: Libraries :: Python Modules
Classifier: Operating System :: OS Independent
Requires-Python: >=3.6
License-File: LICENSE
Dynamic: author
Dynamic: author-email
Dynamic: classifier
Dynamic: description
Dynamic: description-content-type
Dynamic: home-page
Dynamic: keywords
Dynamic: license
Dynamic: license-file
Dynamic: project-url
Dynamic: requires-python
Dynamic: summary
